spconv_cu111.libs/libcudart-6d56b25a.so.11.1.74
spconv/algo.py
spconv/tools.py
spconv/cppconstants.py
spconv/__version__.py
spconv/debug_utils.py
spconv/constants.py
spconv/build.py
spconv/test_utils.py
spconv/core.py
spconv/__init__.py
spconv/core_cc.cpython-37m-x86_64-linux-gnu.so
spconv/csrc/__init__.py
spconv/csrc/sparse/gather.py
spconv/csrc/sparse/maxpool.py
spconv/csrc/sparse/pointops.py
spconv/csrc/sparse/cpu_core.py
spconv/csrc/sparse/__init__.py
spconv/csrc/sparse/all.py
spconv/csrc/sparse/indices.py
spconv/csrc/utils/boxops.py
spconv/csrc/utils/__init__.py
spconv/csrc/hash/core.py
spconv/csrc/hash/__init__.py
spconv/utils/__init__.py
spconv/pytorch/spatial.py
spconv/pytorch/functional.py
spconv/pytorch/modules.py
spconv/pytorch/conv.py
spconv/pytorch/cppcore.py
spconv/pytorch/hash.py
spconv/pytorch/pool.py
spconv/pytorch/ops.py
spconv/pytorch/constants.py
spconv/pytorch/tables.py
spconv/pytorch/core.py
spconv/pytorch/utils.py
spconv/pytorch/identity.py
spconv/pytorch/__init__.py
spconv/core_cc/__init__.pyi
spconv/core_cc/csrc/__init__.pyi
spconv/core_cc/csrc/sparse/__init__.pyi
spconv/core_cc/csrc/sparse/all/ops_cpu1d.pyi
spconv/core_cc/csrc/sparse/all/ops4d.pyi
spconv/core_cc/csrc/sparse/all/ops2d.pyi
spconv/core_cc/csrc/sparse/all/ops1d.pyi
spconv/core_cc/csrc/sparse/all/__init__.pyi
spconv/core_cc/csrc/sparse/all/ops3d.pyi
spconv/core_cc/csrc/sparse/all/ops_cpu2d.pyi
spconv/core_cc/csrc/sparse/all/ops_cpu4d.pyi
spconv/core_cc/csrc/sparse/all/ops_cpu3d.pyi
spconv/core_cc/csrc/utils/boxops.pyi
spconv/core_cc/csrc/utils/__init__.pyi
spconv/core_cc/csrc/hash/__init__.pyi
spconv/core_cc/csrc/hash/core.pyi
spconv/core_cc/cumm/__init__.pyi
spconv/core_cc/cumm/common.pyi
spconv/core_cc/cumm/conv/__init__.pyi
spconv/core_cc/cumm/conv/main.pyi
spconv/core_cc/cumm/gemm/__init__.pyi
spconv/core_cc/cumm/gemm/main.pyi
spconv_cu111-2.1.25.dist-info/top_level.txt
spconv_cu111-2.1.25.dist-info/WHEEL
spconv_cu111-2.1.25.dist-info/METADATA
spconv_cu111-2.1.25.dist-info/RECORD
spconv_cu111-2.1.25.dist-info/LICENSE
