Metadata-Version: 2.1
Name: spconv-cu111
Version: 2.1.25
Summary: spatial sparse convolution
Home-page: https://github.com/traveller59/spconv
Author: Yan Yan
Author-email: yanyan.sub@outlook.com
License: Apache License 2.0
Classifier: License :: OSI Approved :: Apache Software License
Classifier: Programming Language :: Python
Classifier: Programming Language :: Python :: 3
Classifier: Programming Language :: Python :: Implementation :: CPython
Requires-Python: >=3.6
License-File: LICENSE
Requires-Dist: pccm (<0.4.0)
Requires-Dist: ccimport (<0.4.0)
Requires-Dist: pybind11 (>=2.6.0)
Requires-Dist: fire
Requires-Dist: numpy
Requires-Dist: cumm-cu111 (<0.3.0,>=0.2.9)
